rfc5424logging/__init__.py
rfc5424logging/adapter.py
rfc5424logging/handler.py
rfc5424logging/transport.py
rfc5424_logging_handler-1.4.3.dist-info/LICENSE
rfc5424_logging_handler-1.4.3.dist-info/METADATA
rfc5424_logging_handler-1.4.3.dist-info/WHEEL
rfc5424_logging_handler-1.4.3.dist-info/top_level.txt
rfc5424_logging_handler-1.4.3.dist-info/RECORD
