Metadata-Version: 1.1
Name: rfc5424-logging-handler
Version: 1.4.3
Summary: An up-to-date, RFC5424-Compliant syslog handler for the Python logging framework
Home-page: https://github.com/jobec/rfc5424-logging-handler
Author: Joris Beckers
Author-email: joris.beckers@gmail.com
License: BSD
Download-URL: https://pypi.python.org/pypi/rfc5424-logging-handler
Keywords: python logging handler syslog rfc5424
Platform: UNKNOWN
Classifier: Intended Audience :: Developers
Classifier: Operating System :: OS Independent
Classifier: License :: OSI Approved :: BSD License
Classifier: Programming Language :: Python
Classifier: Programming Language :: Python :: 2
Classifier: Programming Language :: Python :: 2.7
Classifier: Programming Language :: Python :: 3
Classifier: Programming Language :: Python :: 3.4
Classifier: Programming Language :: Python :: 3.5
Classifier: Programming Language :: Python :: 3.6
Classifier: Programming Language :: Python :: 3.7
Classifier: Topic :: Software Development :: Libraries :: Python Modules
Classifier: Topic :: System :: Logging
Classifier: Development Status :: 5 - Production/Stable
